ansys/templates/__init__.py
ansys/templates/__main__.py
ansys/templates/cli.py
ansys/templates/paths.py
ansys/templates/testing.py
ansys/templates/utils.py
ansys/templates/licenses/LICENSE_MIT
ansys/templates/licenses/__init__.py
ansys/templates/python/common/cookiecutter.json
ansys/templates/python/common/{{cookiecutter.__project_name_slug}}/.coveragerc
ansys/templates/python/common/{{cookiecutter.__project_name_slug}}/.dockerignore
ansys/templates/python/common/{{cookiecutter.__project_name_slug}}/.flake8
ansys/templates/python/common/{{cookiecutter.__project_name_slug}}/.gitattributes
ansys/templates/python/common/{{cookiecutter.__project_name_slug}}/.gitignore
ansys/templates/python/common/{{cookiecutter.__project_name_slug}}/.pre-commit-config.yaml
ansys/templates/python/common/{{cookiecutter.__project_name_slug}}/AUTHORS
ansys/templates/python/common/{{cookiecutter.__project_name_slug}}/CHANGELOG.md
ansys/templates/python/common/{{cookiecutter.__project_name_slug}}/CODE_OF_CONDUCT.md
ansys/templates/python/common/{{cookiecutter.__project_name_slug}}/CONTRIBUTING.md
ansys/templates/python/common/{{cookiecutter.__project_name_slug}}/CONTRIBUTORS.md
ansys/templates/python/common/{{cookiecutter.__project_name_slug}}/README.rst
ansys/templates/python/common/{{cookiecutter.__project_name_slug}}/azure-pipeline.yml
ansys/templates/python/common/{{cookiecutter.__project_name_slug}}/pyproject.toml
ansys/templates/python/common/{{cookiecutter.__project_name_slug}}/pytest.ini
ansys/templates/python/common/{{cookiecutter.__project_name_slug}}/requirements_build.txt
ansys/templates/python/common/{{cookiecutter.__project_name_slug}}/requirements_doc.txt
ansys/templates/python/common/{{cookiecutter.__project_name_slug}}/requirements_tests.txt
ansys/templates/python/common/{{cookiecutter.__project_name_slug}}/setup.py
ansys/templates/python/common/{{cookiecutter.__project_name_slug}}/tox.ini
ansys_templates-5.1.0.dist-info/entry_points.txt
ansys_templates-5.1.0.dist-info/licenses/COPYING
ansys_templates-5.1.0.dist-info/licenses/LICENSE
ansys_templates-5.1.0.dist-info/WHEEL
ansys_templates-5.1.0.dist-info/METADATA
ansys_templates-5.1.0.dist-info/RECORD
