Metadata-Version: 2.4
Name: ansys-templates
Version: 5.1.0
Summary: Creates Python projects according to PyAnsys guidelines
Author-email: "ANSYS, Inc." <pyansys.core@ansys.com>
Maintainer-email: "ANSYS, Inc." <pyansys.core@ansys.com>
Requires-Python: >=3.9,<4
Classifier: Development Status :: 4 - Beta
Classifier: Programming Language :: Python :: 3
Classifier: Programming Language :: Python :: 3.9
Classifier: Programming Language :: Python :: 3.10
Classifier: Programming Language :: Python :: 3.11
Classifier: Programming Language :: Python :: 3.11
Classifier: Programming Language :: Python :: 3.12
Classifier: License :: OSI Approved :: MIT License
Classifier: Operating System :: OS Independent
License-File: COPYING
License-File: LICENSE
Requires-Dist: importlib-metadata >=4.0
Requires-Dist: click>=7.0,<9.0.0
Requires-Dist: cookiecutter>=2.1.0,<2.3.0
Requires-Dist: isort>=5.10.1
Requires-Dist: ansys-sphinx-theme==1.0.5 ; extra == "doc"
Requires-Dist: numpydoc==1.8.0 ; extra == "doc"
Requires-Dist: Sphinx==8.0.2 ; extra == "doc"
Requires-Dist: sphinx-copybutton==0.5.2 ; extra == "doc"
Requires-Dist: sphinx_design==0.6.1 ; extra == "doc"
Requires-Dist: pytest==8.2.2 ; extra == "tests"
Requires-Dist: pytest-cov==5.0.0 ; extra == "tests"
Project-URL: Documentation, https://templates.ansys.com/
Project-URL: Homepage, https://templates.ansys.com/
Project-URL: Source, https://github.com/ansys/ansys-templates
Project-URL: Tracker, https://github.com/ansys/ansys-templates/issues
Provides-Extra: doc
Provides-Extra: tests
